sdm_modbus/__init__.py
sdm_modbus/espp1.py
sdm_modbus/garo.py
sdm_modbus/meter.py
sdm_modbus/sdm.py
sdm_modbus/taiyedq.py
sdm_modbus-0.7.0.dist-info/LICENSE
sdm_modbus-0.7.0.dist-info/METADATA
sdm_modbus-0.7.0.dist-info/WHEEL
sdm_modbus-0.7.0.dist-info/top_level.txt
sdm_modbus-0.7.0.dist-info/RECORD
