Metadata-Version: 2.1
Name: sdm-modbus
Version: 0.7.0
Summary: Eastron SDM Modbus parser library
Home-page: https://github.com/nmakel/sdm_modbus
Author: nmakel
License: MIT License
Project-URL: Issue Tracker, https://github.com/nmakel/sdm_modbus/issues
Classifier: Development Status :: 4 - Beta
Classifier: Programming Language :: Python :: 3.8
Classifier: Operating System :: OS Independent
Classifier: Environment :: Console
Classifier: Natural Language :: English
Classifier: Intended Audience :: Developers
Classifier: License :: OSI Approved :: MIT License
Requires-Python: >=3.8
License-File: LICENSE
Requires-Dist: pymodbus >=3.5.0
Requires-Dist: pyserial-asyncio >=0.6.0
